<mockup version="4.2" platform="MtWeb" defaultW="1100" defaultH="6000" from="FmLocal" minAllowVersion="4.1" ID="9417448B-1B95-E611-AA7D-B88D12140E82" measureW="1100" measureH="6000" mobileScreenScale="0">
  <controls controlCount="7">
    <control controlID="F05F4095-1B95-E611-AA7D-B88D12140E82" controlTypeID="Image" isShow="True" caption="%E5%9B%BE%E7%89%87" x="0" y="0" w="1100" h="1546" measuredW="150" measuredH="150" zOrder="0" locked="False" sizeLocked="False">
      <controlProperties>
        <basic color="4294967295" borderVisible="False" borderColor="4284900966" isAutoSize="False" status="MsEnabled" opacity="1" isCommentCom="False" canMove="True" alias="" rotation="0"/>
        <states/>
        <verticalScrollbarShow>False</verticalScrollbarShow>
        <verticalScrollbarProgress>0</verticalScrollbarProgress>
        <horizontalScrollbarShow>False</horizontalScrollbarShow>
        <horizontalScrollbarProgress>0</horizontalScrollbarProgress>
        <links eventType="AtClick" animate="AmNone" animateAutoDelay="0" animateDuration="500">
          <link targetPageID="" linkType="ltPageLink" isApplyIncludePage="False" title="%E9%93%BE%E6%8E%A5">
            <area shape="0" alt="" ID="{EE664095-1B95-E611-AA7D-B88D12140E82}" coords="(0,0,1100,1546)"/>
          </link>
        </links>
        <interactiveData>
          <entry title="">
            <area shape="0" alt="" ID="{8E674095-1B95-E611-AA7D-B88D12140E82}" coords="(0,0,1100,1546)"/>
            <events title=""/>
          </entry>
        </interactiveData>
        <rotationAngle>TdZero</rotationAngle>
        <clipShapeType>SbRectangle</clipShapeType>
        <radius>0</radius>
        <radiusIsPercent>False</radiusIsPercent>
        <filterType>MfNone</filterType>
        <filterPencilValue>2</filterPencilValue>
        <filterSketchValue>5</filterSketchValue>
        <URL>95629957D318425219C0B454CC383231.png</URL>
        <FlipHorizontal>False</FlipHorizontal>
        <FlipVertical>False</FlipVertical>
        <fitMode>2</fitMode>
      </controlProperties>
    </control>
    <control controlID="D0AED5BC-2595-E611-AA7D-B88D12140E82" controlTypeID="Shape" isShow="True" caption="%E5%BD%A2%E7%8A%B6" x="264" y="63" w="120" h="45" measuredW="120" measuredH="100" zOrder="1" locked="False" sizeLocked="False">
      <controlProperties>
        <basic color="4294967295" borderVisible="False" borderColor="4284900966" isAutoSize="False" status="MsEnabled" opacity="0" isCommentCom="False" canMove="True" alias="" rotation="0"/>
        <states/>
        <verticalScrollbarShow>False</verticalScrollbarShow>
        <verticalScrollbarProgress>0</verticalScrollbarProgress>
        <horizontalScrollbarShow>False</horizontalScrollbarShow>
        <horizontalScrollbarProgress>0</horizontalScrollbarProgress>
        <links eventType="AtClick" animate="AmNone" animateAutoDelay="0" animateDuration="500">
          <link targetPageID="861B2296-1995-E611-AA7D-B88D12140E82" linkType="ltPageLink" isApplyIncludePage="False" title="%E6%B4%BB%E6%9C%9F%E9%A1%B5">
            <area shape="0" alt="" ID="{382241DA-1B95-E611-AA7D-B88D12140E82}" coords="(0,0,120,45)"/>
          </link>
        </links>
        <interactiveData>
          <entry title="">
            <area shape="0" alt="" ID="{CE2241DA-1B95-E611-AA7D-B88D12140E82}" coords="(0,0,120,45)"/>
            <events title=""/>
          </entry>
        </interactiveData>
        <textSet textColor="4278190080" textSize="14" textFontFamily=".AppleSystemUIFont" lineSpacingMultiple="1" textAlign="HaCenter" textVAlign="VaMiddle" textWordWrap="True" textStyles="[]" useDefaultTextSize="True"/>
        <selectedIndex>-1</selectedIndex>
        <selectedColor>4282501083</selectedColor>
        <textPadding>0</textPadding>
        <shapeBorderType>SbRectangle</shapeBorderType>
        <triangleType>TdZero</triangleType>
        <dashMode>SdSolid</dashMode>
        <rectangleBorderLeftVisible>True</rectangleBorderLeftVisible>
        <rectangleBorderRightVisible>True</rectangleBorderRightVisible>
        <rectangleBorderTopVisible>True</rectangleBorderTopVisible>
        <rectangleBorderBottomVisible>True</rectangleBorderBottomVisible>
        <radius>0</radius>
        <radiusIsPercent>False</radiusIsPercent>
        <thickness>1</thickness>
      </controlProperties>
    </control>
    <control controlID="96F2D5BC-2595-E611-AA7D-B88D12140E82" controlTypeID="Shape" isShow="True" caption="%E5%BD%A2%E7%8A%B6" x="401" y="63" w="120" h="45" measuredW="120" measuredH="100" zOrder="2" locked="False" sizeLocked="False">
      <controlProperties>
        <basic color="4294967295" borderVisible="False" borderColor="4284900966" isAutoSize="False" status="MsEnabled" opacity="0" isCommentCom="False" canMove="True" alias="" rotation="0"/>
        <states/>
        <verticalScrollbarShow>False</verticalScrollbarShow>
        <verticalScrollbarProgress>0</verticalScrollbarProgress>
        <horizontalScrollbarShow>False</horizontalScrollbarShow>
        <horizontalScrollbarProgress>0</horizontalScrollbarProgress>
        <links eventType="AtClick" animate="AmNone" animateAutoDelay="0" animateDuration="500">
          <link targetPageID="C46EAD97-1995-E611-AA7D-B88D12140E82" linkType="ltPageLink" isApplyIncludePage="False" title="%E5%AE%9A%E6%9C%9F%E9%A1%B5">
            <area shape="0" alt="" ID="{382241DA-1B95-E611-AA7D-B88D12140E82}" coords="(0,0,120,45)"/>
          </link>
        </links>
        <interactiveData>
          <entry title="">
            <area shape="0" alt="" ID="{CE2241DA-1B95-E611-AA7D-B88D12140E82}" coords="(0,0,120,45)"/>
            <events title=""/>
          </entry>
        </interactiveData>
        <textSet textColor="4278190080" textSize="14" textFontFamily=".AppleSystemUIFont" lineSpacingMultiple="1" textAlign="HaCenter" textVAlign="VaMiddle" textWordWrap="True" textStyles="[]" useDefaultTextSize="True"/>
        <selectedIndex>-1</selectedIndex>
        <selectedColor>4282501083</selectedColor>
        <textPadding>0</textPadding>
        <shapeBorderType>SbRectangle</shapeBorderType>
        <triangleType>TdZero</triangleType>
        <dashMode>SdSolid</dashMode>
        <rectangleBorderLeftVisible>True</rectangleBorderLeftVisible>
        <rectangleBorderRightVisible>True</rectangleBorderRightVisible>
        <rectangleBorderTopVisible>True</rectangleBorderTopVisible>
        <rectangleBorderBottomVisible>True</rectangleBorderBottomVisible>
        <radius>0</radius>
        <radiusIsPercent>False</radiusIsPercent>
        <thickness>1</thickness>
      </controlProperties>
    </control>
    <control controlID="8E36D6BC-2595-E611-AA7D-B88D12140E82" controlTypeID="Shape" isShow="True" caption="%E5%BD%A2%E7%8A%B6" x="687" y="64" w="120" h="45" measuredW="120" measuredH="100" zOrder="3" locked="False" sizeLocked="False">
      <controlProperties>
        <basic color="4294967295" borderVisible="False" borderColor="4284900966" isAutoSize="False" status="MsEnabled" opacity="0" isCommentCom="False" canMove="True" alias="" rotation="0"/>
        <states/>
        <verticalScrollbarShow>False</verticalScrollbarShow>
        <verticalScrollbarProgress>0</verticalScrollbarProgress>
        <horizontalScrollbarShow>False</horizontalScrollbarShow>
        <horizontalScrollbarProgress>0</horizontalScrollbarProgress>
        <links eventType="AtClick" animate="AmNone" animateAutoDelay="0" animateDuration="500">
          <link targetPageID="C649F09A-1995-E611-AA7D-B88D12140E82" linkType="ltPageLink" isApplyIncludePage="False" title="%E5%AE%89%E5%85%A8%E9%A1%B5">
            <area shape="0" alt="" ID="{382241DA-1B95-E611-AA7D-B88D12140E82}" coords="(0,0,120,45)"/>
          </link>
        </links>
        <interactiveData>
          <entry title="">
            <area shape="0" alt="" ID="{CE2241DA-1B95-E611-AA7D-B88D12140E82}" coords="(0,0,120,45)"/>
            <events title=""/>
          </entry>
        </interactiveData>
        <textSet textColor="4278190080" textSize="14" textFontFamily=".AppleSystemUIFont" lineSpacingMultiple="1" textAlign="HaCenter" textVAlign="VaMiddle" textWordWrap="True" textStyles="[]" useDefaultTextSize="True"/>
        <selectedIndex>-1</selectedIndex>
        <selectedColor>4282501083</selectedColor>
        <textPadding>0</textPadding>
        <shapeBorderType>SbRectangle</shapeBorderType>
        <triangleType>TdZero</triangleType>
        <dashMode>SdSolid</dashMode>
        <rectangleBorderLeftVisible>True</rectangleBorderLeftVisible>
        <rectangleBorderRightVisible>True</rectangleBorderRightVisible>
        <rectangleBorderTopVisible>True</rectangleBorderTopVisible>
        <rectangleBorderBottomVisible>True</rectangleBorderBottomVisible>
        <radius>0</radius>
        <radiusIsPercent>False</radiusIsPercent>
        <thickness>1</thickness>
      </controlProperties>
    </control>
    <control controlID="FC77D6BC-2595-E611-AA7D-B88D12140E82" controlTypeID="Shape" isShow="True" caption="%E5%BD%A2%E7%8A%B6" x="828" y="64" w="120" h="45" measuredW="120" measuredH="100" zOrder="4" locked="False" sizeLocked="False">
      <controlProperties>
        <basic color="4294967295" borderVisible="False" borderColor="4284900966" isAutoSize="False" status="MsEnabled" opacity="0" isCommentCom="False" canMove="True" alias="" rotation="0"/>
        <states/>
        <verticalScrollbarShow>False</verticalScrollbarShow>
        <verticalScrollbarProgress>0</verticalScrollbarProgress>
        <horizontalScrollbarShow>False</horizontalScrollbarShow>
        <horizontalScrollbarProgress>0</horizontalScrollbarProgress>
        <links eventType="AtClick" animate="AmNone" animateAutoDelay="0" animateDuration="500">
          <link targetPageID="D00FDFA9-1995-E611-AA7D-B88D12140E82" linkType="ltPageLink" isApplyIncludePage="False" title="%E5%8A%A0%E5%85%A5%E6%88%91%E4%BB%AC%E9%A1%B5">
            <area shape="0" alt="" ID="{382241DA-1B95-E611-AA7D-B88D12140E82}" coords="(0,0,120,45)"/>
          </link>
        </links>
        <interactiveData>
          <entry title="">
            <area shape="0" alt="" ID="{CE2241DA-1B95-E611-AA7D-B88D12140E82}" coords="(0,0,120,45)"/>
            <events title=""/>
          </entry>
        </interactiveData>
        <textSet textColor="4278190080" textSize="14" textFontFamily=".AppleSystemUIFont" lineSpacingMultiple="1" textAlign="HaCenter" textVAlign="VaMiddle" textWordWrap="True" textStyles="[]" useDefaultTextSize="True"/>
        <selectedIndex>-1</selectedIndex>
        <selectedColor>4282501083</selectedColor>
        <textPadding>0</textPadding>
        <shapeBorderType>SbRectangle</shapeBorderType>
        <triangleType>TdZero</triangleType>
        <dashMode>SdSolid</dashMode>
        <rectangleBorderLeftVisible>True</rectangleBorderLeftVisible>
        <rectangleBorderRightVisible>True</rectangleBorderRightVisible>
        <rectangleBorderTopVisible>True</rectangleBorderTopVisible>
        <rectangleBorderBottomVisible>True</rectangleBorderBottomVisible>
        <radius>0</radius>
        <radiusIsPercent>False</radiusIsPercent>
        <thickness>1</thickness>
      </controlProperties>
    </control>
    <control controlID="34C2D6BC-2595-E611-AA7D-B88D12140E82" controlTypeID="Shape" isShow="True" caption="%E5%BD%A2%E7%8A%B6" x="828" y="19" w="120" h="45" measuredW="120" measuredH="100" zOrder="5" locked="False" sizeLocked="False">
      <controlProperties>
        <basic color="4294967295" borderVisible="False" borderColor="4284900966" isAutoSize="False" status="MsEnabled" opacity="0" isCommentCom="False" canMove="True" alias="" rotation="0"/>
        <states/>
        <verticalScrollbarShow>False</verticalScrollbarShow>
        <verticalScrollbarProgress>0</verticalScrollbarProgress>
        <horizontalScrollbarShow>False</horizontalScrollbarShow>
        <horizontalScrollbarProgress>0</horizontalScrollbarProgress>
        <links eventType="AtClick" animate="AmNone" animateAutoDelay="0" animateDuration="500">
          <link targetPageID="AEFF3E36-6990-E611-88E4-B88D12140E82" linkType="ltPageLink" isApplyIncludePage="False" title="%E6%B3%A8%E5%86%8C%E9%A1%B5">
            <area shape="0" alt="" ID="{382241DA-1B95-E611-AA7D-B88D12140E82}" coords="(0,0,120,45)"/>
          </link>
        </links>
        <interactiveData>
          <entry title="">
            <area shape="0" alt="" ID="{CE2241DA-1B95-E611-AA7D-B88D12140E82}" coords="(0,0,120,45)"/>
            <events title=""/>
          </entry>
        </interactiveData>
        <textSet textColor="4278190080" textSize="14" textFontFamily=".AppleSystemUIFont" lineSpacingMultiple="1" textAlign="HaCenter" textVAlign="VaMiddle" textWordWrap="True" textStyles="[]" useDefaultTextSize="True"/>
        <selectedIndex>-1</selectedIndex>
        <selectedColor>4282501083</selectedColor>
        <textPadding>0</textPadding>
        <shapeBorderType>SbRectangle</shapeBorderType>
        <triangleType>TdZero</triangleType>
        <dashMode>SdSolid</dashMode>
        <rectangleBorderLeftVisible>True</rectangleBorderLeftVisible>
        <rectangleBorderRightVisible>True</rectangleBorderRightVisible>
        <rectangleBorderTopVisible>True</rectangleBorderTopVisible>
        <rectangleBorderBottomVisible>True</rectangleBorderBottomVisible>
        <radius>0</radius>
        <radiusIsPercent>False</radiusIsPercent>
        <thickness>1</thickness>
      </controlProperties>
    </control>
    <control controlID="5000D7BC-2595-E611-AA7D-B88D12140E82" controlTypeID="Shape" isShow="True" caption="%E5%BD%A2%E7%8A%B6" x="549" y="67" w="120" h="45" measuredW="120" measuredH="100" zOrder="6" locked="False" sizeLocked="False">
      <controlProperties>
        <basic color="4294967295" borderVisible="False" borderColor="4284900966" isAutoSize="False" status="MsEnabled" opacity="0" isCommentCom="False" canMove="True" alias="" rotation="0"/>
        <states/>
        <verticalScrollbarShow>False</verticalScrollbarShow>
        <verticalScrollbarProgress>0</verticalScrollbarProgress>
        <horizontalScrollbarShow>False</horizontalScrollbarShow>
        <horizontalScrollbarProgress>0</horizontalScrollbarProgress>
        <links eventType="AtClick" animate="AmNone" animateAutoDelay="0" animateDuration="500">
          <link targetPageID="CC964499-1995-E611-AA7D-B88D12140E82" linkType="ltPageLink" isApplyIncludePage="False" title="%E7%BE%8E%E9%87%91%E9%A1%B5">
            <area shape="0" alt="" ID="{382241DA-1B95-E611-AA7D-B88D12140E82}" coords="(0,0,120,45)"/>
          </link>
        </links>
        <interactiveData>
          <entry title="">
            <area shape="0" alt="" ID="{CE2241DA-1B95-E611-AA7D-B88D12140E82}" coords="(0,0,120,45)"/>
            <events title=""/>
          </entry>
        </interactiveData>
        <textSet textColor="4278190080" textSize="14" textFontFamily=".AppleSystemUIFont" lineSpacingMultiple="1" textAlign="HaCenter" textVAlign="VaMiddle" textWordWrap="True" textStyles="[]" useDefaultTextSize="True"/>
        <selectedIndex>-1</selectedIndex>
        <selectedColor>4282501083</selectedColor>
        <textPadding>0</textPadding>
        <shapeBorderType>SbRectangle</shapeBorderType>
        <triangleType>TdZero</triangleType>
        <dashMode>SdSolid</dashMode>
        <rectangleBorderLeftVisible>True</rectangleBorderLeftVisible>
        <rectangleBorderRightVisible>True</rectangleBorderRightVisible>
        <rectangleBorderTopVisible>True</rectangleBorderTopVisible>
        <rectangleBorderBottomVisible>True</rectangleBorderBottomVisible>
        <radius>0</radius>
        <radiusIsPercent>False</radiusIsPercent>
        <thickness>1</thickness>
      </controlProperties>
    </control>
  </controls>
  <param>
    <backgroundColor>4294967295</backgroundColor>
    <fontFamily/>
    <guideLines/>
  </param>
</mockup>